{
    "results":[
        {
            "username": "Gil21",
            "password":"1234567",
            "email": "gildebil2@gmail.com",
            "proffesions":["Mechanic", "Baker"],
            "massages":[],
            "age":"22",
            "ismobile": "true",
            "phonenumber":"0528708464"
        },
        {
            "username": "Daniel8",
            "password":"1234567",
            "email": "daniel.brizel@gmail.com",
            "proffesions":["Mechanic", "Electrician"],
            "massages":[],
            "age":"23",
            "ismobile": "true",
            "phonenumber":"0556608006"
        },
        {
            "username": "guyTs5",
            "password":"1234567",
            "email": "guyts@outlook.com",
            "proffesions":["Baker", "Electrician"],
            "massages":[],
            "age":"23",
            "ismobile": "false",
            "phonenumber":"0535326241"
        }

    ]
}